odil/.gitignore
odil/__init__.py
odil/backend.py
odil/cache.py
odil/core.py
odil/core_min.py
odil/history.py
odil/io.py
odil/linsolver.py
odil/odil.mplstyle
odil/optimizer.py
odil/plot.py
odil/plotutil.py
odil/requirements.txt
odil/runtime.py
odil/util.py
odil-0.1.8.dist-info/METADATA
odil-0.1.8.dist-info/WHEEL
odil-0.1.8.dist-info/licenses/LICENSE
odil-0.1.8.dist-info/RECORD
