Metadata-Version: 2.3
Name: odil
Version: 0.1.8
Summary: ODIL (Optimizing a DIscrete Loss) is a framework for solving inverse problems for differential equations
Project-URL: Homepage, https://github.com/cselab/odil
Project-URL: Issues, https://github.com/cselab/odil/issues
Author-email: Petr Karnakov <pkarnakov@gmail.com>, Sergey Litvinov <slitvinov@gmail.com>
License-File: LICENSE
Classifier: License :: OSI Approved :: MIT License
Classifier: Operating System :: OS Independent
Classifier: Programming Language :: Python :: 3
Requires-Dist: numpy
Requires-Dist: psutil
Requires-Dist: scipy
